IrisKuangjiaZhongwenWendang/README.md
IrisKuangjiaZhongwenWendang/__init__.py
IrisKuangjiaZhongwenWendang/__main__.py
IrisKuangjiaZhongwenWendang/file.epub
IrisKuangjiaZhongwenWendang/index.html
IrisKuangjiaZhongwenWendang/css/__init__.py
IrisKuangjiaZhongwenWendang/css/annotations.css
IrisKuangjiaZhongwenWendang/css/main.css
IrisKuangjiaZhongwenWendang/css/normalize.css
IrisKuangjiaZhongwenWendang/css/popup.css
IrisKuangjiaZhongwenWendang/font/__init__.py
IrisKuangjiaZhongwenWendang/font/fontello.eot
IrisKuangjiaZhongwenWendang/font/fontello.svg
IrisKuangjiaZhongwenWendang/font/fontello.ttf
IrisKuangjiaZhongwenWendang/font/fontello.woff
IrisKuangjiaZhongwenWendang/img/__init__.py
IrisKuangjiaZhongwenWendang/img/annotator-glyph-sprite.png
IrisKuangjiaZhongwenWendang/img/annotator-icon-sprite.png
IrisKuangjiaZhongwenWendang/img/apple-touch-icon.png
IrisKuangjiaZhongwenWendang/img/cancelfullscreen.png
IrisKuangjiaZhongwenWendang/img/close.png
IrisKuangjiaZhongwenWendang/img/fullscreen.png
IrisKuangjiaZhongwenWendang/img/loader.gif
IrisKuangjiaZhongwenWendang/img/menu-icon.png
IrisKuangjiaZhongwenWendang/img/save.png
IrisKuangjiaZhongwenWendang/img/saved.png
IrisKuangjiaZhongwenWendang/img/settings-s.png
IrisKuangjiaZhongwenWendang/img/settings.png
IrisKuangjiaZhongwenWendang/img/star.png
IrisKuangjiaZhongwenWendang/js/__init__.py
IrisKuangjiaZhongwenWendang/js/epub.js
IrisKuangjiaZhongwenWendang/js/epub.min.js
IrisKuangjiaZhongwenWendang/js/epub.min.map
IrisKuangjiaZhongwenWendang/js/hooks.min.js
IrisKuangjiaZhongwenWendang/js/hooks.min.map
IrisKuangjiaZhongwenWendang/js/reader.js
IrisKuangjiaZhongwenWendang/js/reader.js.map
IrisKuangjiaZhongwenWendang/js/reader.min.js
IrisKuangjiaZhongwenWendang/js/reader.min.map
IrisKuangjiaZhongwenWendang/js/hooks/__init__.py
IrisKuangjiaZhongwenWendang/js/hooks/extensions/__init__.py
IrisKuangjiaZhongwenWendang/js/hooks/extensions/highlight.js
IrisKuangjiaZhongwenWendang/js/libs/__init__.py
iris_kuangjia_zhongwen_wendang-2024.3.5.0.dist-info/METADATA
iris_kuangjia_zhongwen_wendang-2024.3.5.0.dist-info/WHEEL
iris_kuangjia_zhongwen_wendang-2024.3.5.0.dist-info/entry_points.txt
iris_kuangjia_zhongwen_wendang-2024.3.5.0.dist-info/top_level.txt
iris_kuangjia_zhongwen_wendang-2024.3.5.0.dist-info/RECORD
